[
  {
    "id": 1,
    "title": "Сезонная скидка 15%",
    "description": "На все виды сервисного обслуживания до конца месяца. Успейте записаться!",
    "price_old": "от 50 000 ₽",
    "price_new": "от 42 500 ₽",
    "features": [
      "диагностика",
      "ремонт",
      "обслуживание"
    ],
    "icon": "",
    "created_by": 1,
    "created_at": "2026-05-08T12:00:00.000Z",
    "updated_at": null,
    "is_active": 1
  },
  {
    "id": 2,
    "title": "Бесплатная диагностика",
    "description": "При первом обращении диагностика оборудования бесплатно. Экономия до 5 000 ₽.",
    "price_old": "5 000 ₽",
    "price_new": "0 ₽",
    "features": [
      "первый визит",
      "полный отчёт"
    ],
    "icon": "",
    "created_by": 1,
    "created_at": "2026-05-07T10:00:00.000Z",
    "updated_at": null,
    "is_active": 1
  }
]